scanitd/__init__.py
scanitd/base/__init__.py
scanitd/base/basic.py
scanitd/base/basic_read.py
scanitd/base/cigar.py
scanitd/cli/__init__.py
scanitd/cli/cli.py
scanitd/inference/__init__.py
scanitd/inference/helper.py
scanitd/inference/main.py
scanitd/inference/sr_resuer.py
scanitd/mtype.py
scanitd/py.typed
scanitd/writer/__init__.py
scanitd/writer/vcf_writer.py
scanitd/writer/writer.py
scanitd-0.9.1.dist-info/LICENSE
scanitd-0.9.1.dist-info/METADATA
scanitd-0.9.1.dist-info/WHEEL
scanitd-0.9.1.dist-info/entry_points.txt
scanitd-0.9.1.dist-info/RECORD
