Metadata-Version: 2.1
Name: scanitd
Version: 0.9.1
Summary: ScanITD
Home-page: https://github.com/ylab-hi/ScanITD
License: MIT
Author: Ting-You Wang
Author-email: tywang@northwestern.edu
Requires-Python: >=3.9,<4.0
Classifier: Development Status :: 4 - Beta
Classifier: License :: OSI Approved :: MIT License
Classifier: Programming Language :: Python :: 3
Classifier: Programming Language :: Python :: 3.9
Classifier: Programming Language :: Python :: 3.10
Classifier: Programming Language :: Python :: 3.11
Classifier: Programming Language :: Python :: 3.12
Classifier: Programming Language :: Python :: 3.13
Classifier: Programming Language :: Python :: 3 :: Only
Requires-Dist: loguru (>=0.7.0,<0.8.0)
Requires-Dist: numpy (>=2.0.0,<3.0.0)
Requires-Dist: psutil (>=5.9.5,<6.0.0)
Requires-Dist: pyfaidx (>=0.7.2,<0.8.0)
Requires-Dist: pysam (>=0.22.0,<0.23.0)
Requires-Dist: rich (>=13.7.0,<14.0.0)
Requires-Dist: ssw-py (>=1.0.1,<2.0.0)
Requires-Dist: typer (>=0.12.5,<0.13.0)
Project-URL: Changelog, https://github.com/ylab-hi/ScanITD/releases
Project-URL: Documentation, https://scanitd.readthedocs.io
Project-URL: Repository, https://github.com/ylab-hi/ScanITD
